[
  {
    "estudios": "Estudios de bachiller cursados en la U.E Colegio Don Bosco, actualmente estudiando ingeniería en computación en la Universidad De Oriente(UDO).",
    "objetivo": "Mi objetivo es ganar experiencia laboral trabajando en la programación web.",
    "formacion": "2014 - Bachiller graduado del colegio: U.E Colegio Don Bosco."
  },
  {
    "curso1": "2018 - Learn HTML5 Programming From Scratch(10.5h) - Eduonix Learning Solutions.",
    "curso2": "2018 - CSS para principiantes, Tus proyectos toman vida(3h) - Daniel Fernandez Velazquez.",
    "curso3": "2018 - JavaScript: de cero hasta los detalles(8h) - Fernando Herrera Analista de Sistemas y Desarrollador Web."
  }
]
